odoo/addons/mgmtsystem_nonconformity_project/README.rst
odoo/addons/mgmtsystem_nonconformity_project/__init__.py
odoo/addons/mgmtsystem_nonconformity_project/__manifest__.py
odoo/addons/mgmtsystem_nonconformity_project/i18n/de.po
odoo/addons/mgmtsystem_nonconformity_project/i18n/fr.po
odoo/addons/mgmtsystem_nonconformity_project/i18n/it.po
odoo/addons/mgmtsystem_nonconformity_project/i18n/mgmtsystem_nonconformity_project.pot
odoo/addons/mgmtsystem_nonconformity_project/i18n/nb.po
odoo/addons/mgmtsystem_nonconformity_project/i18n/pt_BR.po
odoo/addons/mgmtsystem_nonconformity_project/i18n/vi.po
odoo/addons/mgmtsystem_nonconformity_project/models/__init__.py
odoo/addons/mgmtsystem_nonconformity_project/models/mgmtsystem_nonconformity_project.py
odoo/addons/mgmtsystem_nonconformity_project/readme/CONTRIBUTORS.rst
odoo/addons/mgmtsystem_nonconformity_project/readme/DESCRIPTION.rst
odoo/addons/mgmtsystem_nonconformity_project/static/description/icon.png
odoo/addons/mgmtsystem_nonconformity_project/static/description/index.html
odoo/addons/mgmtsystem_nonconformity_project/static/src/img/icon.png
odoo/addons/mgmtsystem_nonconformity_project/tests/__init__.py
odoo/addons/mgmtsystem_nonconformity_project/tests/test_nonconformity_project.py
odoo/addons/mgmtsystem_nonconformity_project/views/mgmtsystem_nonconformity_project.xml
odoo12_addon_mgmtsystem_nonconformity_project-12.0.1.0.0.99.dev9.dist-info/METADATA
odoo12_addon_mgmtsystem_nonconformity_project-12.0.1.0.0.99.dev9.dist-info/WHEEL
odoo12_addon_mgmtsystem_nonconformity_project-12.0.1.0.0.99.dev9.dist-info/top_level.txt
odoo12_addon_mgmtsystem_nonconformity_project-12.0.1.0.0.99.dev9.dist-info/RECORD
